{
  "way/52042017": "Västergatan",
  "way/131695661": "Stadiongatan",
  "node/253357180": "Stockholmsvägen",
  "node/429998727": "Centralplan",
  "node/444845100": "Centralplan",
  "node/444853562": "Lilla Nygatan",
  "node/444876188": "Pilgatan",
  "node/493899996": "Heleneholmsstigen",
  "node/514143378": "Hjälmarekajen",
  "way/1036504139": "Södra Förstadsgatan",
  "way/1036504147": "Södra Förstadsgatan",
  "way/1091108904": "Lilla Torg",
  "way/1092638248": "Engelbrektsgatan",
  "way/1304005493": "Amiralsgatan",
  "node/1364768136": "Spångatan",
  "node/1385696595": "Gyllenpalmsgatan",
  "node/1677335991": "Centralplan",
  "node/1677336035": "Lokgatan",
  "node/1691174377": "Krossverksgatan",
  "node/1812871205": "Tessins väg",
  "node/2293728923": "Skomakaregatan",
  "node/2402822591": "Pilgatan",
  "node/2408201658": "Sankt Johannesgatan",
  "node/2606814827": "Trelleborgsgatan",
  "node/2732141551": "Sankt Johannesplan",
  "node/3355797056": "Karlskronaplan",
  "node/3357955289": "Västergatan",
  "node/3361577188": "Stora Nygatan",
  "node/3402696470": "Centralplan",
  "node/3402696488": "Sankt Johannesgatan",
  "node/3414497905": "Kalendegatan",
  "node/3986086966": "Adelgatan",
  "node/4237208425": "Sankt Johannesgatan",
  "node/4496973300": "Neptunigatan",
  "node/4496973302": "Neptunigatan",
  "node/4523387997": "Amiralsgatan",
  "node/5384441206": "Linnégatan",
  "node/5643775270": "Per Albin Hanssons väg",
  "node/5894539182": "Baltzarsgatan",
  "node/6385559696": "Industrigatan",
  "node/6611723095": "Ärtholmsvägen",
  "node/8072638355": "Lundavägen",
  "node/8078194461": "Regementsgatan",
  "node/9949588099": "Triangeln",
  "node/9949588101": "Triangeln",
  "node/10754157912": "Eriksfältsgatan",
  "node/10754157934": "Per Albin Hanssons väg",
  "node/10754157954": "Trelleborgsvägen",
  "node/10754157959": "Trelleborgsvägen",
  "node/10754158023": "Djäknegatan",
  "node/10754158038": "Hyllie stationsväg",
  "node/10754158040": "Hyllie stationsväg",
  "node/10754158052": "Hyllie stationsväg",
  "node/10756703231": "Köpenhamnsvägen",
  "node/11179361788": "Gustaf Rydbergsgatan",
  "node/11640709599": "Friisgatan",
  "node/11763806803": "Spångatan",
  "node/11780230899": "Regementsgatan",
  "node/11780230900": "Regementsgatan",
  "node/11791943025": "Triangeln",
  "node/11886748891": "Malmborgsgatan",
  "node/11886749193": "Stadt Hamburgsgatan",
  "node/12106766501": "Per Albin Hanssons väg",
  "node/12161689467": "Storgatan",
  "node/12455685503": "Plaskgränd",
  "node/13014857199": "Fredsgatan",
  "node/13387301367": "Dockplatsen",
  "node/13666976701": "Emblas gränd"
}